tp_requests/__init__.py
tp_requests/http.py
tp_requests/mqtt.py
tp_requests/ws.py
tp_requests-2025.10.10.dist-info/LICENSE
tp_requests-2025.10.10.dist-info/METADATA
tp_requests-2025.10.10.dist-info/WHEEL
tp_requests-2025.10.10.dist-info/top_level.txt
tp_requests-2025.10.10.dist-info/RECORD
