Metadata-Version: 2.1
Name: tp-requests
Version: 2025.10.10
Summary: Send the HTTP/ MQTT/ WEBSOCKET Request
Author-email: TP Cyber Security <tpcybersec2023@gmail.com>
License: MIT
Project-URL: Homepage, https://github.com/TPCyberSec/TP-Requests
Keywords: TPCyberSec,TP_Requests,TP_HTTP_REQUEST,TP_MQTT_REQUEST,TP_WEBSOCKET_REQUEST
Classifier: Programming Language :: Python :: 3
License-File: LICENSE
Requires-Dist: tp-http-request-response-parser>=2025.9.30
